LICENSE
MANIFEST.in
README.rst
setup.py
lemon_pages.egg-info/PKG-INFO
lemon_pages.egg-info/SOURCES.txt
lemon_pages.egg-info/dependency_links.txt
lemon_pages.egg-info/requires.txt
lemon_pages.egg-info/top_level.txt
pages/__init__.py
pages/admin.py
pages/forms.py
pages/middleware.py
pages/models.py
pages/search_indexes.py
pages/settings.py
pages/views.py
pages/widgets.py
pages/locale/ru/LC_MESSAGES/django.mo
pages/locale/ru/LC_MESSAGES/django.po
pages/templates/search/indexes/pages/page_text.txt